Library/methods/__init__.py
Library/methods/read_logs.py
GooLogBot-1.0.0.dist-info/LICENSE
GooLogBot-1.0.0.dist-info/METADATA
GooLogBot-1.0.0.dist-info/WHEEL
GooLogBot-1.0.0.dist-info/top_level.txt
GooLogBot-1.0.0.dist-info/RECORD
