Metadata-Version: 2.1
Name: GooLogBot
Version: 1.0.0
Summary: A lightweight program for reading log files and reporting rows, logged at specific levels, in a google chat
Author-email: David Marienburg <dmarienburg@pps.net>
License: MIT License        
Project-URL: Homepage, https://github.com/dmarienburg/GooLogBot
Project-URL: Bug Tracker, https://github.com/dmarienburg/GooLogBot/issues
Keywords: logging,chat-bot,google-chat
Classifier: Programming Language :: Python :: 3
Classifier: License :: OSI Approved :: MIT License
Classifier: Operating System :: OS Independent
Requires-Python: >=3.0.0
License-File: LICENSE
